dpdata_abinit/__init__.py
dpdata_abinit/abihist.py
dpdata_abinit/histnc.py
dpdata_abinit-0.0.4.dist-info/LICENSE
dpdata_abinit-0.0.4.dist-info/METADATA
dpdata_abinit-0.0.4.dist-info/WHEEL
dpdata_abinit-0.0.4.dist-info/entry_points.txt
dpdata_abinit-0.0.4.dist-info/top_level.txt
dpdata_abinit-0.0.4.dist-info/zip-safe
dpdata_abinit-0.0.4.dist-info/RECORD
