Metadata-Version: 2.1
Name: dpdata-abinit
Version: 0.0.4
Summary: Dpdata plugin of ABINIT hist file
License-File: LICENSE
Requires-Dist: abipy
Requires-Dist: ase
Requires-Dist: dpdata
Requires-Dist: numpy
